Metadata-Version: 2.1
Name: golfprofile
Version: 0.0.1
Summary: golfprofile by RashawatCoding
Home-page: https://github.com/RashawatCoding/golfprofile
Author: RashawatCoding
Author-email: 123456@gmail.com
License: MIT
Download-URL: https://github.com/RashawatCoding/golfprofile/archive/v0.0.1.zip
Keywords: profile,Uncle Engineer
Platform: UNKNOWN
Classifier: Development Status :: 3 - Alpha
Classifier: Intended Audience :: Education
Classifier: Topic :: Utilities
Classifier: License :: OSI Approved :: MIT License
Classifier: Programming Language :: Python :: 3
Classifier: Programming Language :: Python :: 3.4
Classifier: Programming Language :: Python :: 3.5
Classifier: Programming Language :: Python :: 3.6
Classifier: Programming Language :: Python :: 3.7
Classifier: Programming Language :: Python :: 3.8
Classifier: Programming Language :: Python :: 3.9
Classifier: Programming Language :: Python :: 3.10
License-File: LICENSE.txt
